{
  "timestamp": "2025-10-30T23:17:01.447788",
  "data": {
    "appearances": {
      "title": "Appearances",
      "stats": [
        {
          "title": "Men's Team Appearances",
          "value": "9"
        },
        {
          "title": "Minutes Played",
          "value": "675"
        },
        {
          "title": "Starts",
          "value": "9"
        },
        {
          "title": "Subbed On / Off",
          "value": "0/6"
        }
      ]
    },
    "fouls": {
      "yellowCards": {
        "title": "Yellow Cards",
        "value": "0"
      },
      "redCards": {
        "title": "Red Cards",
        "value": "0"
      },
      "foulsDrawn": {
        "title": "Fouls Drawn",
        "value": "8"
      },
      "foulsCommitted": {
        "title": "Fouls Committed",
        "value": "1"
      }
    },
    "passes": {
      "title": "Passes",
      "forwards": {
        "title": "Forward",
        "value": "41"
      },
      "backwards": {
        "title": "Back",
        "value": "60"
      },
      "left": {
        "title": "Left",
        "value": "70"
      },
      "right": {
        "title": "Right",
        "value": "47"
      }
    },
    "scoredWith": {
      "title": "Scored With",
      "head": {
        "title": "Head",
        "value": "0"
      },
      "leftFoot": {
        "title": "Left Foot",
        "value": "2"
      },
      "rightFoot": {
        "title": "Right Foot",
        "value": "0"
      },
      "penalties": {
        "title": "Penalties",
        "value": "0"
      },
      "freeKicks": {
        "title": "Free Kicks",
        "value": "1"
      }
    },
    "goals": {
      "title": "Goals",
      "playerRankingLabel": "Overall Team Ranking",
      "playerRankingValue": "2",
      "teamRankingLabel": "Team Rankings",
      "goalsBoxLabel": "Goals Inside/Outside Box",
      "goalsOutsideBox": 50.0,
      "goalsInsideBox": 50.0,
      "playerAvatar": {
        "image": {
          "id": "editorial/people/first-team/2025-26/Pedro_Neto_2025-26_profile_with_patch_headshot-removebg",
          "title": "editorial/people/first-team/2025-26/Pedro_Neto_2025-26_profile_with_patch_headshot-removebg",
          "description": "",
          "credit": "",
          "file": {
            "fileName": "editorial/people/first-team/2025-26/Pedro_Neto_2025-26_profile_with_patch_headshot-removebg",
            "contentType": "image",
            "type": "upload",
            "format": "png",
            "url": "http://img.chelseafc.com/image/upload/v1756766634/editorial/people/first-team/2025-26/Pedro_Neto_2025-26_profile_with_patch_headshot-removebg.png",
            "urlObject": {
              "baseUrl": "https://res.cloudinary.com/",
              "cloudName": "chelsea-production",
              "resourceType": "image",
              "type": "upload",
              "publicId": "editorial/people/first-team/2025-26/Pedro_Neto_2025-26_profile_with_patch_headshot-removebg"
            },
            "details": {
              "size": 13348891,
              "transformations": "",
              "image": {
                "width": 3333,
                "height": 3333
              }
            }
          },
          "coordinates": []
        }
      },
      "teamRankings": [
        {
          "playerRank": "1st",
          "rankValue": 1,
          "playerAvatar": {
            "lastName": "Caicedo",
            "image": {
              "id": "editorial/people/first-team/2025-26/Moises_Caicedo_2025-26_profile_with_patch_headshot-removebg",
              "title": "editorial/people/first-team/2025-26/Moises_Caicedo_2025-26_profile_with_patch_headshot-removebg",
              "description": "",
              "credit": "",
              "file": {
                "fileName": "editorial/people/first-team/2025-26/Moises_Caicedo_2025-26_profile_with_patch_headshot-removebg",
                "contentType": "image",
                "type": "upload",
                "format": "png",
                "url": "http://img.chelseafc.com/image/upload/v1756766521/editorial/people/first-team/2025-26/Moises_Caicedo_2025-26_profile_with_patch_headshot-removebg.png",
                "urlObject": {
                  "baseUrl": "https://res.cloudinary.com/",
                  "cloudName": "chelsea-production",
                  "resourceType": "image",
                  "type": "upload",
                  "publicId": "editorial/people/first-team/2025-26/Moises_Caicedo_2025-26_profile_with_patch_headshot-removebg"
                },
                "details": {
                  "size": 12213259,
                  "transformations": "",
                  "image": {
                    "width": 3333,
                    "height": 3333
                  }
                }
              },
              "coordinates": []
            },
            "profileLink": {
              "id": "46fa3d4c-8728-4e40-bf8d-a78f0fab9384",
              "title": "Caicedo",
              "url": "/en/teams/profile/moises-caicedo",
              "isExternal": false,
              "isActive": false
            }
          },
          "playerAdditionalStat": "3"
        },
        {
          "playerRank": "1st",
          "rankValue": 1,
          "playerAvatar": {
            "lastName": "Fernandez",
            "image": {
              "id": "editorial/people/first-team/2025-26/Enzo_Fernandez_2025-26_profile_with_patch_headshot-removebg",
              "title": "editorial/people/first-team/2025-26/Enzo_Fernandez_2025-26_profile_with_patch_headshot-removebg",
              "description": "",
              "credit": "",
              "file": {
                "fileName": "editorial/people/first-team/2025-26/Enzo_Fernandez_2025-26_profile_with_patch_headshot-removebg",
                "contentType": "image",
                "type": "upload",
                "format": "png",
                "url": "http://img.chelseafc.com/image/upload/v1756766288/editorial/people/first-team/2025-26/Enzo_Fernandez_2025-26_profile_with_patch_headshot-removebg.png",
                "urlObject": {
                  "baseUrl": "https://res.cloudinary.com/",
                  "cloudName": "chelsea-production",
                  "resourceType": "image",
                  "type": "upload",
                  "publicId": "editorial/people/first-team/2025-26/Enzo_Fernandez_2025-26_profile_with_patch_headshot-removebg"
                },
                "details": {
                  "size": 14142518,
                  "transformations": "",
                  "image": {
                    "width": 3333,
                    "height": 3333
                  }
                }
              },
              "coordinates": []
            },
            "profileLink": {
              "id": "591add3a-bba3-4dba-ba16-93edfc05bdbb",
              "title": "Fernandez",
              "url": "/en/teams/profile/enzo-fernandez",
              "isExternal": false,
              "isActive": false
            }
          },
          "playerAdditionalStat": "3"
        },
        {
          "playerRank": "2nd",
          "rankValue": 2,
          "playerAvatar": {
            "lastName": "Chalobah",
            "image": {
              "id": "editorial/people/first-team/2025-26/Trevoh_Chalobah_2025-26_profile_with_patch_headshot-removebg",
              "title": "editorial/people/first-team/2025-26/Trevoh_Chalobah_2025-26_profile_with_patch_headshot-removebg",
              "description": "",
              "credit": "",
              "file": {
                "fileName": "editorial/people/first-team/2025-26/Trevoh_Chalobah_2025-26_profile_with_patch_headshot-removebg",
                "contentType": "image",
                "type": "upload",
                "format": "png",
                "url": "http://img.chelseafc.com/image/upload/v1756766685/editorial/people/first-team/2025-26/Trevoh_Chalobah_2025-26_profile_with_patch_headshot-removebg.png",
                "urlObject": {
                  "baseUrl": "https://res.cloudinary.com/",
                  "cloudName": "chelsea-production",
                  "resourceType": "image",
                  "type": "upload",
                  "publicId": "editorial/people/first-team/2025-26/Trevoh_Chalobah_2025-26_profile_with_patch_headshot-removebg"
                },
                "details": {
                  "size": 13655926,
                  "transformations": "",
                  "image": {
                    "width": 3333,
                    "height": 3333
                  }
                }
              },
              "coordinates": []
            },
            "profileLink": {
              "id": "b39d5678-46cb-4a48-bb19-cef52c9296ff",
              "title": "Chalobah",
              "url": "/en/teams/profile/trevoh-chalobah",
              "isExternal": false,
              "isActive": false
            }
          },
          "playerAdditionalStat": "2"
        },
        {
          "playerRank": "2nd",
          "rankValue": 2,
          "playerAvatar": {
            "lastName": "Pedro",
            "image": {
              "id": "editorial/people/first-team/2025-26/Joao_Pedro_2025-26_profile_with_patch_headshot_-removebg",
              "title": "editorial/people/first-team/2025-26/Joao_Pedro_2025-26_profile_with_patch_headshot_-removebg",
              "description": "",
              "credit": "",
              "file": {
                "fileName": "editorial/people/first-team/2025-26/Joao_Pedro_2025-26_profile_with_patch_headshot_-removebg",
                "contentType": "image",
                "type": "upload",
                "format": "png",
                "url": "http://img.chelseafc.com/image/upload/v1756847578/editorial/people/first-team/2025-26/Joao_Pedro_2025-26_profile_with_patch_headshot_-removebg.png",
                "urlObject": {
                  "baseUrl": "https://res.cloudinary.com/",
                  "cloudName": "chelsea-production",
                  "resourceType": "image",
                  "type": "upload",
                  "publicId": "editorial/people/first-team/2025-26/Joao_Pedro_2025-26_profile_with_patch_headshot_-removebg"
                },
                "details": {
                  "size": 14380038,
                  "transformations": "",
                  "image": {
                    "width": 3333,
                    "height": 3333
                  }
                }
              },
              "coordinates": []
            },
            "profileLink": {
              "id": "625ccd1c-b7ba-47ef-a727-c84bad58dbeb",
              "title": "Pedro",
              "url": "/en/teams/profile/joao-pedro",
              "isExternal": false,
              "isActive": false
            }
          },
          "playerAdditionalStat": "2"
        },
        {
          "playerRank": "2nd",
          "rankValue": 2,
          "playerAvatar": {
            "lastName": "Neto",
            "image": {
              "id": "editorial/people/first-team/2025-26/Pedro_Neto_2025-26_profile_with_patch_headshot-removebg",
              "title": "editorial/people/first-team/2025-26/Pedro_Neto_2025-26_profile_with_patch_headshot-removebg",
              "description": "",
              "credit": "",
              "file": {
                "fileName": "editorial/people/first-team/2025-26/Pedro_Neto_2025-26_profile_with_patch_headshot-removebg",
                "contentType": "image",
                "type": "upload",
                "format": "png",
                "url": "http://img.chelseafc.com/image/upload/v1756766634/editorial/people/first-team/2025-26/Pedro_Neto_2025-26_profile_with_patch_headshot-removebg.png",
                "urlObject": {
                  "baseUrl": "https://res.cloudinary.com/",
                  "cloudName": "chelsea-production",
                  "resourceType": "image",
                  "type": "upload",
                  "publicId": "editorial/people/first-team/2025-26/Pedro_Neto_2025-26_profile_with_patch_headshot-removebg"
                },
                "details": {
                  "size": 13348891,
                  "transformations": "",
                  "image": {
                    "width": 3333,
                    "height": 3333
                  }
                }
              },
              "coordinates": []
            },
            "profileLink": {
              "id": "2b06e076-660f-446f-a9d1-69b0cadc257b",
              "title": "Neto",
              "url": "/en/teams/profile/pedro-neto",
              "isExternal": false,
              "isActive": false
            }
          },
          "playerAdditionalStat": "2"
        },
        {
          "playerRank": "3rd",
          "rankValue": 3,
          "playerAvatar": {
            "lastName": "Garnacho",
            "image": {
              "id": "editorial/people/first-team/2025-26/Alejandro_Garnacho_profile_headshot_2025-26-removebg",
              "title": "editorial/people/first-team/2025-26/Alejandro_Garnacho_profile_headshot_2025-26-removebg",
              "description": "",
              "credit": "",
              "file": {
                "fileName": "editorial/people/first-team/2025-26/Alejandro_Garnacho_profile_headshot_2025-26-removebg",
                "contentType": "image",
                "type": "upload",
                "format": "png",
                "url": "http://img.chelseafc.com/image/upload/v1756735497/editorial/people/first-team/2025-26/Alejandro_Garnacho_profile_headshot_2025-26-removebg.png",
                "urlObject": {
                  "baseUrl": "https://res.cloudinary.com/",
                  "cloudName": "chelsea-production",
                  "resourceType": "image",
                  "type": "upload",
                  "publicId": "editorial/people/first-team/2025-26/Alejandro_Garnacho_profile_headshot_2025-26-removebg"
                },
                "details": {
                  "size": 12505616,
                  "transformations": "",
                  "image": {
                    "width": 3333,
                    "height": 3333
                  }
                }
              },
              "coordinates": []
            },
            "profileLink": {
              "id": "91324610-ff4b-456c-b614-724e487bc200",
              "title": "Garnacho",
              "url": "/en/teams/profile/alejandro-garnacho",
              "isExternal": false,
              "isActive": false
            }
          },
          "playerAdditionalStat": "1"
        },
        {
          "playerRank": "3rd",
          "rankValue": 3,
          "playerAvatar": {
            "lastName": "Acheampong",
            "image": {
              "id": "editorial/people/first-team/2025-26/Josh_Acheampong_2025-26_profile_with_patch_headshot-removebg",
              "title": "editorial/people/first-team/2025-26/Josh_Acheampong_2025-26_profile_with_patch_headshot-removebg",
              "description": "",
              "credit": "",
              "file": {
                "fileName": "editorial/people/first-team/2025-26/Josh_Acheampong_2025-26_profile_with_patch_headshot-removebg",
                "contentType": "image",
                "type": "upload",
                "format": "png",
                "url": "http://img.chelseafc.com/image/upload/v1756766430/editorial/people/first-team/2025-26/Josh_Acheampong_2025-26_profile_with_patch_headshot-removebg.png",
                "urlObject": {
                  "baseUrl": "https://res.cloudinary.com/",
                  "cloudName": "chelsea-production",
                  "resourceType": "image",
                  "type": "upload",
                  "publicId": "editorial/people/first-team/2025-26/Josh_Acheampong_2025-26_profile_with_patch_headshot-removebg"
                },
                "details": {
                  "size": 13534562,
                  "transformations": "",
                  "image": {
                    "width": 3333,
                    "height": 3333
                  }
                }
              },
              "coordinates": []
            },
            "profileLink": {
              "id": "a0403d7f-2028-454b-8450-af9b3cdddb05",
              "title": "Acheampong",
              "url": "/en/teams/profile/josh-acheampong",
              "isExternal": false,
              "isActive": false
            }
          },
          "playerAdditionalStat": "1"
        },
        {
          "playerRank": "3rd",
          "rankValue": 3,
          "playerAvatar": {
            "lastName": "James",
            "image": {
              "id": "editorial/people/first-team/2025-26/Reece_James_2025-26_profile_with_patch_headshot-removebg",
              "title": "editorial/people/first-team/2025-26/Reece_James_2025-26_profile_with_patch_headshot-removebg",
              "description": "",
              "credit": "",
              "file": {
                "fileName": "editorial/people/first-team/2025-26/Reece_James_2025-26_profile_with_patch_headshot-removebg",
                "contentType": "image",
                "type": "upload",
                "format": "png",
                "url": "http://img.chelseafc.com/image/upload/v1756766586/editorial/people/first-team/2025-26/Reece_James_2025-26_profile_with_patch_headshot-removebg.png",
                "urlObject": {
                  "baseUrl": "https://res.cloudinary.com/",
                  "cloudName": "chelsea-production",
                  "resourceType": "image",
                  "type": "upload",
                  "publicId": "editorial/people/first-team/2025-26/Reece_James_2025-26_profile_with_patch_headshot-removebg"
                },
                "details": {
                  "size": 14056446,
                  "transformations": "",
                  "image": {
                    "width": 3333,
                    "height": 3333
                  }
                }
              },
              "coordinates": []
            },
            "profileLink": {
              "id": "a0ffe6ed-9cc8-404f-94d2-a96b521193c5",
              "title": "James",
              "url": "/en/teams/profile/reece-james",
              "isExternal": false,
              "isActive": false
            }
          },
          "playerAdditionalStat": "1"
        },
        {
          "playerRank": "3rd",
          "rankValue": 3,
          "playerAvatar": {
            "lastName": "Willian",
            "image": {
              "id": "editorial/people/first-team/2025-26/Estevao_headshot_2025-26_avatar-removebg",
              "title": "editorial/people/first-team/2025-26/Estevao_headshot_2025-26_avatar-removebg",
              "description": "",
              "credit": "",
              "file": {
                "fileName": "editorial/people/first-team/2025-26/Estevao_headshot_2025-26_avatar-removebg",
                "contentType": "image",
                "type": "upload",
                "format": "png",
                "url": "http://img.chelseafc.com/image/upload/v1754420045/editorial/people/first-team/2025-26/Estevao_headshot_2025-26_avatar-removebg.png",
                "urlObject": {
                  "baseUrl": "https://res.cloudinary.com/",
                  "cloudName": "chelsea-production",
                  "resourceType": "image",
                  "type": "upload",
                  "publicId": "editorial/people/first-team/2025-26/Estevao_headshot_2025-26_avatar-removebg"
                },
                "details": {
                  "size": 4410590,
                  "transformations": "",
                  "image": {
                    "width": 1882,
                    "height": 1882
                  }
                }
              },
              "coordinates": []
            },
            "profileLink": {
              "id": "5c6fc688-66a9-410f-93d2-f32c0a3068bf",
              "title": "Willian",
              "url": "/en/teams/profile/estevao",
              "isExternal": false,
              "isActive": false
            }
          },
          "playerAdditionalStat": "1"
        },
        {
          "playerRank": "3rd",
          "rankValue": 3,
          "playerAvatar": {
            "lastName": "Palmer ",
            "image": {
              "id": "editorial/people/first-team/2025-26/Cole_Palmer_2025-26_profile_with_headshot_avatar-removebg",
              "title": "editorial/people/first-team/2025-26/Cole_Palmer_2025-26_profile_with_headshot_avatar-removebg",
              "description": "",
              "credit": "",
              "file": {
                "fileName": "editorial/people/first-team/2025-26/Cole_Palmer_2025-26_profile_with_headshot_avatar-removebg",
                "contentType": "image",
                "type": "upload",
                "format": "png",
                "url": "http://img.chelseafc.com/image/upload/v1756766299/editorial/people/first-team/2025-26/Cole_Palmer_2025-26_profile_with_headshot_avatar-removebg.png",
                "urlObject": {
                  "baseUrl": "https://res.cloudinary.com/",
                  "cloudName": "chelsea-production",
                  "resourceType": "image",
                  "type": "upload",
                  "publicId": "editorial/people/first-team/2025-26/Cole_Palmer_2025-26_profile_with_headshot_avatar-removebg"
                },
                "details": {
                  "size": 12827579,
                  "transformations": "",
                  "image": {
                    "width": 3333,
                    "height": 3333
                  }
                }
              },
              "coordinates": []
            },
            "profileLink": {
              "id": "ca5ce730-6665-4c69-9732-05ea485c4c6c",
              "title": "Palmer ",
              "url": "/en/teams/profile/cole-palmer",
              "isExternal": false,
              "isActive": false
            }
          },
          "playerAdditionalStat": "1"
        }
      ],
      "stats": [
        {
          "title": "Total Goals",
          "value": "2"
        },
        {
          "title": "Goals Per Match",
          "value": "0.22"
        },
        {
          "title": "Minutes Per Goal",
          "value": "338"
        }
      ]
    },
    "passSuccess": {
      "title": "Pass Success Rate",
      "playerRankingLabel": "Overall Team Ranking",
      "playerRankingValue": "15",
      "playerRankingPercent": "85",
      "teamRankingLabel": "Team Rankings",
      "stats": [
        {
          "title": "Total Passes",
          "value": "218"
        },
        {
          "title": "Key Passes",
          "value": "12"
        },
        {
          "title": "Successful Crosses",
          "value": "10"
        },
        {
          "title": "Assists",
          "value": "2"
        }
      ],
      "teamRankings": [
        {
          "playerRank": "1st",
          "overallTeamRankingPercent": "95",
          "rankValue": 1,
          "playerAvatar": {
            "lastName": "Lavia",
            "image": {
              "id": "editorial/people/first-team/2025-26/Romeo_Lavia_2025-26_profile_with_patch_headshot-removebg",
              "title": "editorial/people/first-team/2025-26/Romeo_Lavia_2025-26_profile_with_patch_headshot-removebg",
              "description": "",
              "credit": "",
              "file": {
                "fileName": "editorial/people/first-team/2025-26/Romeo_Lavia_2025-26_profile_with_patch_headshot-removebg",
                "contentType": "image",
                "type": "upload",
                "format": "png",
                "url": "http://img.chelseafc.com/image/upload/v1756766632/editorial/people/first-team/2025-26/Romeo_Lavia_2025-26_profile_with_patch_headshot-removebg.png",
                "urlObject": {
                  "baseUrl": "https://res.cloudinary.com/",
                  "cloudName": "chelsea-production",
                  "resourceType": "image",
                  "type": "upload",
                  "publicId": "editorial/people/first-team/2025-26/Romeo_Lavia_2025-26_profile_with_patch_headshot-removebg"
                },
                "details": {
                  "size": 14517908,
                  "transformations": "",
                  "image": {
                    "width": 3333,
                    "height": 3333
                  }
                }
              },
              "coordinates": []
            },
            "profileLink": {
              "id": "e4ded103-54bb-48fb-b2b6-028911328129",
              "title": "Lavia",
              "url": "/en/teams/profile/romeo-lavia",
              "isExternal": false,
              "isActive": false
            }
          },
          "playerAdditionalStat": "95%"
        },
        {
          "playerRank": "2nd",
          "overallTeamRankingPercent": "93",
          "rankValue": 2,
          "playerAvatar": {
            "lastName": "Badiashile",
            "image": {
              "id": "editorial/people/first-team/2025-26/Benoit_Badiashile_2025-26_profile_with_patch_headshot-removebg",
              "title": "editorial/people/first-team/2025-26/Benoit_Badiashile_2025-26_profile_with_patch_headshot-removebg",
              "description": "",
              "credit": "",
              "file": {
                "fileName": "editorial/people/first-team/2025-26/Benoit_Badiashile_2025-26_profile_with_patch_headshot-removebg",
                "contentType": "image",
                "type": "upload",
                "format": "png",
                "url": "http://img.chelseafc.com/image/upload/v1756766327/editorial/people/first-team/2025-26/Benoit_Badiashile_2025-26_profile_with_patch_headshot-removebg.png",
                "urlObject": {
                  "baseUrl": "https://res.cloudinary.com/",
                  "cloudName": "chelsea-production",
                  "resourceType": "image",
                  "type": "upload",
                  "publicId": "editorial/people/first-team/2025-26/Benoit_Badiashile_2025-26_profile_with_patch_headshot-removebg"
                },
                "details": {
                  "size": 16223442,
                  "transformations": "",
                  "image": {
                    "width": 3333,
                    "height": 3333
                  }
                }
              },
              "coordinates": []
            },
            "profileLink": {
              "id": "312d2609-cf3e-4e5b-b602-bed73b46f8c6",
              "title": "Badiashile",
              "url": "/en/teams/profile/benoit-badiashile",
              "isExternal": false,
              "isActive": false
            }
          },
          "playerAdditionalStat": "93%"
        },
        {
          "playerRank": "3rd",
          "overallTeamRankingPercent": "92",
          "rankValue": 3,
          "playerAvatar": {
            "lastName": "Acheampong",
            "image": {
              "id": "editorial/people/first-team/2025-26/Josh_Acheampong_2025-26_profile_with_patch_headshot-removebg",
              "title": "editorial/people/first-team/2025-26/Josh_Acheampong_2025-26_profile_with_patch_headshot-removebg",
              "description": "",
              "credit": "",
              "file": {
                "fileName": "editorial/people/first-team/2025-26/Josh_Acheampong_2025-26_profile_with_patch_headshot-removebg",
                "contentType": "image",
                "type": "upload",
                "format": "png",
                "url": "http://img.chelseafc.com/image/upload/v1756766430/editorial/people/first-team/2025-26/Josh_Acheampong_2025-26_profile_with_patch_headshot-removebg.png",
                "urlObject": {
                  "baseUrl": "https://res.cloudinary.com/",
                  "cloudName": "chelsea-production",
                  "resourceType": "image",
                  "type": "upload",
                  "publicId": "editorial/people/first-team/2025-26/Josh_Acheampong_2025-26_profile_with_patch_headshot-removebg"
                },
                "details": {
                  "size": 13534562,
                  "transformations": "",
                  "image": {
                    "width": 3333,
                    "height": 3333
                  }
                }
              },
              "coordinates": []
            },
            "profileLink": {
              "id": "2017a7db-fb60-42f4-9405-5b20f2ff86b0",
              "title": "Acheampong",
              "url": "/en/teams/profile/josh-acheampong",
              "isExternal": false,
              "isActive": false
            }
          },
          "playerAdditionalStat": "92%"
        },
        {
          "playerRank": "4th",
          "overallTeamRankingPercent": "92",
          "rankValue": 4,
          "playerAvatar": {
            "lastName": "Chalobah",
            "image": {
              "id": "editorial/people/first-team/2025-26/Trevoh_Chalobah_2025-26_profile_with_patch_headshot-removebg",
              "title": "editorial/people/first-team/2025-26/Trevoh_Chalobah_2025-26_profile_with_patch_headshot-removebg",
              "description": "",
              "credit": "",
              "file": {
                "fileName": "editorial/people/first-team/2025-26/Trevoh_Chalobah_2025-26_profile_with_patch_headshot-removebg",
                "contentType": "image",
                "type": "upload",
                "format": "png",
                "url": "http://img.chelseafc.com/image/upload/v1756766685/editorial/people/first-team/2025-26/Trevoh_Chalobah_2025-26_profile_with_patch_headshot-removebg.png",
                "urlObject": {
                  "baseUrl": "https://res.cloudinary.com/",
                  "cloudName": "chelsea-production",
                  "resourceType": "image",
                  "type": "upload",
                  "publicId": "editorial/people/first-team/2025-26/Trevoh_Chalobah_2025-26_profile_with_patch_headshot-removebg"
                },
                "details": {
                  "size": 13655926,
                  "transformations": "",
                  "image": {
                    "width": 3333,
                    "height": 3333
                  }
                }
              },
              "coordinates": []
            },
            "profileLink": {
              "id": "978f736a-45ef-4055-b7a1-13651c0ccb7e",
              "title": "Chalobah",
              "url": "/en/teams/profile/trevoh-chalobah",
              "isExternal": false,
              "isActive": false
            }
          },
          "playerAdditionalStat": "92%"
        },
        {
          "playerRank": "5th",
          "overallTeamRankingPercent": "92",
          "rankValue": 5,
          "playerAvatar": {
            "lastName": "Fofana",
            "image": {
              "id": "editorial/people/first-team/2025-26/Wesley_Fofana_2025-26_profile_with_patch_headshot-removebg",
              "title": "editorial/people/first-team/2025-26/Wesley_Fofana_2025-26_profile_with_patch_headshot-removebg",
              "description": "",
              "credit": "",
              "file": {
                "fileName": "editorial/people/first-team/2025-26/Wesley_Fofana_2025-26_profile_with_patch_headshot-removebg",
                "contentType": "image",
                "type": "upload",
                "format": "png",
                "url": "http://img.chelseafc.com/image/upload/v1756766696/editorial/people/first-team/2025-26/Wesley_Fofana_2025-26_profile_with_patch_headshot-removebg.png",
                "urlObject": {
                  "baseUrl": "https://res.cloudinary.com/",
                  "cloudName": "chelsea-production",
                  "resourceType": "image",
                  "type": "upload",
                  "publicId": "editorial/people/first-team/2025-26/Wesley_Fofana_2025-26_profile_with_patch_headshot-removebg"
                },
                "details": {
                  "size": 14161320,
                  "transformations": "",
                  "image": {
                    "width": 3333,
                    "height": 3333
                  }
                }
              },
              "coordinates": []
            },
            "profileLink": {
              "id": "74fa40ae-514d-4c57-bc65-0b012e13bab8",
              "title": "Fofana",
              "url": "/en/teams/profile/wesley-fofana",
              "isExternal": false,
              "isActive": false
            }
          },
          "playerAdditionalStat": "92%"
        },
        {
          "playerRank": "6th",
          "overallTeamRankingPercent": "91",
          "rankValue": 6,
          "playerAvatar": {
            "lastName": "Caicedo",
            "image": {
              "id": "editorial/people/first-team/2025-26/Moises_Caicedo_2025-26_profile_with_patch_headshot-removebg",
              "title": "editorial/people/first-team/2025-26/Moises_Caicedo_2025-26_profile_with_patch_headshot-removebg",
              "description": "",
              "credit": "",
              "file": {
                "fileName": "editorial/people/first-team/2025-26/Moises_Caicedo_2025-26_profile_with_patch_headshot-removebg",
                "contentType": "image",
                "type": "upload",
                "format": "png",
                "url": "http://img.chelseafc.com/image/upload/v1756766521/editorial/people/first-team/2025-26/Moises_Caicedo_2025-26_profile_with_patch_headshot-removebg.png",
                "urlObject": {
                  "baseUrl": "https://res.cloudinary.com/",
                  "cloudName": "chelsea-production",
                  "resourceType": "image",
                  "type": "upload",
                  "publicId": "editorial/people/first-team/2025-26/Moises_Caicedo_2025-26_profile_with_patch_headshot-removebg"
                },
                "details": {
                  "size": 12213259,
                  "transformations": "",
                  "image": {
                    "width": 3333,
                    "height": 3333
                  }
                }
              },
              "coordinates": []
            },
            "profileLink": {
              "id": "01dfdb75-24b1-489b-876d-5edf6acd9056",
              "title": "Caicedo",
              "url": "/en/teams/profile/moises-caicedo",
              "isExternal": false,
              "isActive": false
            }
          },
          "playerAdditionalStat": "91%"
        },
        {
          "playerRank": "7th",
          "overallTeamRankingPercent": "91",
          "rankValue": 7,
          "playerAvatar": {
            "lastName": "Gittens",
            "image": {
              "id": "editorial/people/first-team/2025-26/Jamie_Gittens_profile_2025-26_headshot-removebg",
              "title": "editorial/people/first-team/2025-26/Jamie_Gittens_profile_2025-26_headshot-removebg",
              "description": "",
              "credit": "",
              "file": {
                "fileName": "editorial/people/first-team/2025-26/Jamie_Gittens_profile_2025-26_headshot-removebg",
                "contentType": "image",
                "type": "upload",
                "format": "png",
                "url": "http://img.chelseafc.com/image/upload/v1756485798/editorial/people/first-team/2025-26/Jamie_Gittens_profile_2025-26_headshot-removebg.png",
                "urlObject": {
                  "baseUrl": "https://res.cloudinary.com/",
                  "cloudName": "chelsea-production",
                  "resourceType": "image",
                  "type": "upload",
                  "publicId": "editorial/people/first-team/2025-26/Jamie_Gittens_profile_2025-26_headshot-removebg"
                },
                "details": {
                  "size": 12994837,
                  "transformations": "",
                  "image": {
                    "width": 3333,
                    "height": 3333
                  }
                }
              },
              "coordinates": []
            },
            "profileLink": {
              "id": "266530e6-c060-45f1-9a9e-e6f1706b46a3",
              "title": "Gittens",
              "url": "/en/teams/profile/jamie-gittens",
              "isExternal": false,
              "isActive": false
            }
          },
          "playerAdditionalStat": "91%"
        },
        {
          "playerRank": "7th",
          "overallTeamRankingPercent": "91",
          "rankValue": 7,
          "playerAvatar": {
            "lastName": "Buonanotte",
            "image": {
              "id": "editorial/people/first-team/2025-26/Facundo_Buonanotte_profile_headshot_2025-26-removebg",
              "title": "editorial/people/first-team/2025-26/Facundo_Buonanotte_profile_headshot_2025-26-removebg",
              "description": "",
              "credit": "",
              "file": {
                "fileName": "editorial/people/first-team/2025-26/Facundo_Buonanotte_profile_headshot_2025-26-removebg",
                "contentType": "image",
                "type": "upload",
                "format": "png",
                "url": "http://img.chelseafc.com/image/upload/v1756739612/editorial/people/first-team/2025-26/Facundo_Buonanotte_profile_headshot_2025-26-removebg.png",
                "urlObject": {
                  "baseUrl": "https://res.cloudinary.com/",
                  "cloudName": "chelsea-production",
                  "resourceType": "image",
                  "type": "upload",
                  "publicId": "editorial/people/first-team/2025-26/Facundo_Buonanotte_profile_headshot_2025-26-removebg"
                },
                "details": {
                  "size": 14720482,
                  "transformations": "",
                  "image": {
                    "width": 3333,
                    "height": 3333
                  }
                }
              },
              "coordinates": []
            },
            "profileLink": {
              "id": "7a1a61e1-86d3-4a3e-8544-c3332b74652a",
              "title": "Buonanotte",
              "url": "/en/teams/profile/facundo-buonanotte",
              "isExternal": false,
              "isActive": false
            }
          },
          "playerAdditionalStat": "91%"
        },
        {
          "playerRank": "8th",
          "overallTeamRankingPercent": "90",
          "rankValue": 8,
          "playerAvatar": {
            "lastName": "Adarabioyo",
            "image": {
              "id": "editorial/people/first-team/2025-26/Tosin_Adarabioyo_2025-26_profile_with_patch_headshot-removebg",
              "title": "editorial/people/first-team/2025-26/Tosin_Adarabioyo_2025-26_profile_with_patch_headshot-removebg",
              "description": "",
              "credit": "",
              "file": {
                "fileName": "editorial/people/first-team/2025-26/Tosin_Adarabioyo_2025-26_profile_with_patch_headshot-removebg",
                "contentType": "image",
                "type": "upload",
                "format": "png",
                "url": "http://img.chelseafc.com/image/upload/v1756766673/editorial/people/first-team/2025-26/Tosin_Adarabioyo_2025-26_profile_with_patch_headshot-removebg.png",
                "urlObject": {
                  "baseUrl": "https://res.cloudinary.com/",
                  "cloudName": "chelsea-production",
                  "resourceType": "image",
                  "type": "upload",
                  "publicId": "editorial/people/first-team/2025-26/Tosin_Adarabioyo_2025-26_profile_with_patch_headshot-removebg"
                },
                "details": {
                  "size": 13547357,
                  "transformations": "",
                  "image": {
                    "width": 3333,
                    "height": 3333
                  }
                }
              },
              "coordinates": []
            },
            "profileLink": {
              "id": "570f1137-eca9-4a42-a478-7a97ab8f2bf1",
              "title": "Adarabioyo",
              "url": "/en/teams/profile/tosin-adarabioyo",
              "isExternal": false,
              "isActive": false
            }
          },
          "playerAdditionalStat": "90%"
        },
        {
          "playerRank": "9th",
          "overallTeamRankingPercent": "90",
          "rankValue": 9,
          "playerAvatar": {
            "lastName": "James",
            "image": {
              "id": "editorial/people/first-team/2025-26/Reece_James_2025-26_profile_with_patch_headshot-removebg",
              "title": "editorial/people/first-team/2025-26/Reece_James_2025-26_profile_with_patch_headshot-removebg",
              "description": "",
              "credit": "",
              "file": {
                "fileName": "editorial/people/first-team/2025-26/Reece_James_2025-26_profile_with_patch_headshot-removebg",
                "contentType": "image",
                "type": "upload",
                "format": "png",
                "url": "http://img.chelseafc.com/image/upload/v1756766586/editorial/people/first-team/2025-26/Reece_James_2025-26_profile_with_patch_headshot-removebg.png",
                "urlObject": {
                  "baseUrl": "https://res.cloudinary.com/",
                  "cloudName": "chelsea-production",
                  "resourceType": "image",
                  "type": "upload",
                  "publicId": "editorial/people/first-team/2025-26/Reece_James_2025-26_profile_with_patch_headshot-removebg"
                },
                "details": {
                  "size": 14056446,
                  "transformations": "",
                  "image": {
                    "width": 3333,
                    "height": 3333
                  }
                }
              },
              "coordinates": []
            },
            "profileLink": {
              "id": "efed987c-2444-4908-b05b-c8162f98cbf8",
              "title": "James",
              "url": "/en/teams/profile/reece-james",
              "isExternal": false,
              "isActive": false
            }
          },
          "playerAdditionalStat": "90%"
        },
        {
          "playerRank": "10th",
          "overallTeamRankingPercent": "89",
          "rankValue": 10,
          "playerAvatar": {
            "lastName": "Hato ",
            "image": {
              "id": "editorial/people/first-team/2025-26/Jorrel_Hato_headshot_2025-26_avatar-removebg",
              "title": "editorial/people/first-team/2025-26/Jorrel_Hato_headshot_2025-26_avatar-removebg",
              "description": "",
              "credit": "",
              "file": {
                "fileName": "editorial/people/first-team/2025-26/Jorrel_Hato_headshot_2025-26_avatar-removebg",
                "contentType": "image",
                "type": "upload",
                "format": "png",
                "url": "http://img.chelseafc.com/image/upload/v1754296775/editorial/people/first-team/2025-26/Jorrel_Hato_headshot_2025-26_avatar-removebg.png",
                "urlObject": {
                  "baseUrl": "https://res.cloudinary.com/",
                  "cloudName": "chelsea-production",
                  "resourceType": "image",
                  "type": "upload",
                  "publicId": "editorial/people/first-team/2025-26/Jorrel_Hato_headshot_2025-26_avatar-removebg"
                },
                "details": {
                  "size": 14372516,
                  "transformations": "",
                  "image": {
                    "width": 3333,
                    "height": 3333
                  }
                }
              },
              "coordinates": []
            },
            "profileLink": {
              "id": "80e063d1-e945-41cf-839e-6523a906d3cf",
              "title": "Hato ",
              "url": "/en/teams/profile/jorrel-hato",
              "isExternal": false,
              "isActive": false
            }
          },
          "playerAdditionalStat": "89%"
        },
        {
          "playerRank": "11th",
          "overallTeamRankingPercent": "88",
          "rankValue": 11,
          "playerAvatar": {
            "lastName": "Gusto",
            "image": {
              "id": "editorial/people/first-team/2025-26/Malo_Gusto_2025-26_profile_with_patch_headshot-removebg",
              "title": "editorial/people/first-team/2025-26/Malo_Gusto_2025-26_profile_with_patch_headshot-removebg",
              "description": "",
              "credit": "",
              "file": {
                "fileName": "editorial/people/first-team/2025-26/Malo_Gusto_2025-26_profile_with_patch_headshot-removebg",
                "contentType": "image",
                "type": "upload",
                "format": "png",
                "url": "http://img.chelseafc.com/image/upload/v1756766544/editorial/people/first-team/2025-26/Malo_Gusto_2025-26_profile_with_patch_headshot-removebg.png",
                "urlObject": {
                  "baseUrl": "https://res.cloudinary.com/",
                  "cloudName": "chelsea-production",
                  "resourceType": "image",
                  "type": "upload",
                  "publicId": "editorial/people/first-team/2025-26/Malo_Gusto_2025-26_profile_with_patch_headshot-removebg"
                },
                "details": {
                  "size": 13927271,
                  "transformations": "",
                  "image": {
                    "width": 3333,
                    "height": 3333
                  }
                }
              },
              "coordinates": []
            },
            "profileLink": {
              "id": "bb16152c-313c-4880-9d36-c412e2867cb6",
              "title": "Gusto",
              "url": "/en/teams/profile/malo-gusto",
              "isExternal": false,
              "isActive": false
            }
          },
          "playerAdditionalStat": "88%"
        },
        {
          "playerRank": "12th",
          "overallTeamRankingPercent": "88",
          "rankValue": 12,
          "playerAvatar": {
            "lastName": "Cucurella",
            "image": {
              "id": "editorial/people/first-team/2025-26/Marc_Cucurella_2025-26_profile_with_patch_headshot-removebg",
              "title": "editorial/people/first-team/2025-26/Marc_Cucurella_2025-26_profile_with_patch_headshot-removebg",
              "description": "",
              "credit": "",
              "file": {
                "fileName": "editorial/people/first-team/2025-26/Marc_Cucurella_2025-26_profile_with_patch_headshot-removebg",
                "contentType": "image",
                "type": "upload",
                "format": "png",
                "url": "http://img.chelseafc.com/image/upload/v1756766504/editorial/people/first-team/2025-26/Marc_Cucurella_2025-26_profile_with_patch_headshot-removebg.png",
                "urlObject": {
                  "baseUrl": "https://res.cloudinary.com/",
                  "cloudName": "chelsea-production",
                  "resourceType": "image",
                  "type": "upload",
                  "publicId": "editorial/people/first-team/2025-26/Marc_Cucurella_2025-26_profile_with_patch_headshot-removebg"
                },
                "details": {
                  "size": 15893159,
                  "transformations": "",
                  "image": {
                    "width": 3333,
                    "height": 3333
                  }
                }
              },
              "coordinates": []
            },
            "profileLink": {
              "id": "7dc3d261-425e-4c6c-b571-b39d0edbff91",
              "title": "Cucurella",
              "url": "/en/teams/profile/marc-cucurella",
              "isExternal": false,
              "isActive": false
            }
          },
          "playerAdditionalStat": "88%"
        },
        {
          "playerRank": "13th",
          "overallTeamRankingPercent": "87",
          "rankValue": 13,
          "playerAvatar": {
            "lastName": "George",
            "image": {
              "id": "editorial/people/first-team/2025-26/Tyrique_George_2025-26_profile_with_patch_headshot-removebg",
              "title": "editorial/people/first-team/2025-26/Tyrique_George_2025-26_profile_with_patch_headshot-removebg",
              "description": "",
              "credit": "",
              "file": {
                "fileName": "editorial/people/first-team/2025-26/Tyrique_George_2025-26_profile_with_patch_headshot-removebg",
                "contentType": "image",
                "type": "upload",
                "format": "png",
                "url": "http://img.chelseafc.com/image/upload/v1756849790/editorial/people/first-team/2025-26/Tyrique_George_2025-26_profile_with_patch_headshot-removebg.png",
                "urlObject": {
                  "baseUrl": "https://res.cloudinary.com/",
                  "cloudName": "chelsea-production",
                  "resourceType": "image",
                  "type": "upload",
                  "publicId": "editorial/people/first-team/2025-26/Tyrique_George_2025-26_profile_with_patch_headshot-removebg"
                },
                "details": {
                  "size": 13284449,
                  "transformations": "",
                  "image": {
                    "width": 3333,
                    "height": 3333
                  }
                }
              },
              "coordinates": []
            },
            "profileLink": {
              "id": "d2c6e57b-bbcd-48fb-b67c-e114435b1971",
              "title": "George",
              "url": "/en/teams/profile/tyrique-george",
              "isExternal": false,
              "isActive": false
            }
          },
          "playerAdditionalStat": "87%"
        },
        {
          "playerRank": "14th",
          "overallTeamRankingPercent": "85",
          "rankValue": 14,
          "playerAvatar": {
            "lastName": "Garnacho",
            "image": {
              "id": "editorial/people/first-team/2025-26/Alejandro_Garnacho_profile_headshot_2025-26-removebg",
              "title": "editorial/people/first-team/2025-26/Alejandro_Garnacho_profile_headshot_2025-26-removebg",
              "description": "",
              "credit": "",
              "file": {
                "fileName": "editorial/people/first-team/2025-26/Alejandro_Garnacho_profile_headshot_2025-26-removebg",
                "contentType": "image",
                "type": "upload",
                "format": "png",
                "url": "http://img.chelseafc.com/image/upload/v1756735497/editorial/people/first-team/2025-26/Alejandro_Garnacho_profile_headshot_2025-26-removebg.png",
                "urlObject": {
                  "baseUrl": "https://res.cloudinary.com/",
                  "cloudName": "chelsea-production",
                  "resourceType": "image",
                  "type": "upload",
                  "publicId": "editorial/people/first-team/2025-26/Alejandro_Garnacho_profile_headshot_2025-26-removebg"
                },
                "details": {
                  "size": 12505616,
                  "transformations": "",
                  "image": {
                    "width": 3333,
                    "height": 3333
                  }
                }
              },
              "coordinates": []
            },
            "profileLink": {
              "id": "ec661570-9ce1-4d8d-8cbe-782c8b5cd1e8",
              "title": "Garnacho",
              "url": "/en/teams/profile/alejandro-garnacho",
              "isExternal": false,
              "isActive": false
            }
          },
          "playerAdditionalStat": "85%"
        },
        {
          "playerRank": "15th",
          "overallTeamRankingPercent": "85",
          "rankValue": 15,
          "playerAvatar": {
            "lastName": "Neto",
            "image": {
              "id": "editorial/people/first-team/2025-26/Pedro_Neto_2025-26_profile_with_patch_headshot-removebg",
              "title": "editorial/people/first-team/2025-26/Pedro_Neto_2025-26_profile_with_patch_headshot-removebg",
              "description": "",
              "credit": "",
              "file": {
                "fileName": "editorial/people/first-team/2025-26/Pedro_Neto_2025-26_profile_with_patch_headshot-removebg",
                "contentType": "image",
                "type": "upload",
                "format": "png",
                "url": "http://img.chelseafc.com/image/upload/v1756766634/editorial/people/first-team/2025-26/Pedro_Neto_2025-26_profile_with_patch_headshot-removebg.png",
                "urlObject": {
                  "baseUrl": "https://res.cloudinary.com/",
                  "cloudName": "chelsea-production",
                  "resourceType": "image",
                  "type": "upload",
                  "publicId": "editorial/people/first-team/2025-26/Pedro_Neto_2025-26_profile_with_patch_headshot-removebg"
                },
                "details": {
                  "size": 13348891,
                  "transformations": "",
                  "image": {
                    "width": 3333,
                    "height": 3333
                  }
                }
              },
              "coordinates": []
            },
            "profileLink": {
              "id": "daadfb3a-35d0-4b26-bd5d-919f0ddc7ab3",
              "title": "Neto",
              "url": "/en/teams/profile/pedro-neto",
              "isExternal": false,
              "isActive": false
            }
          },
          "playerAdditionalStat": "85%"
        },
        {
          "playerRank": "16th",
          "overallTeamRankingPercent": "85",
          "rankValue": 16,
          "playerAvatar": {
            "lastName": "Willian",
            "image": {
              "id": "editorial/people/first-team/2025-26/Estevao_headshot_2025-26_avatar-removebg",
              "title": "editorial/people/first-team/2025-26/Estevao_headshot_2025-26_avatar-removebg",
              "description": "",
              "credit": "",
              "file": {
                "fileName": "editorial/people/first-team/2025-26/Estevao_headshot_2025-26_avatar-removebg",
                "contentType": "image",
                "type": "upload",
                "format": "png",
                "url": "http://img.chelseafc.com/image/upload/v1754420045/editorial/people/first-team/2025-26/Estevao_headshot_2025-26_avatar-removebg.png",
                "urlObject": {
                  "baseUrl": "https://res.cloudinary.com/",
                  "cloudName": "chelsea-production",
                  "resourceType": "image",
                  "type": "upload",
                  "publicId": "editorial/people/first-team/2025-26/Estevao_headshot_2025-26_avatar-removebg"
                },
                "details": {
                  "size": 4410590,
                  "transformations": "",
                  "image": {
                    "width": 1882,
                    "height": 1882
                  }
                }
              },
              "coordinates": []
            },
            "profileLink": {
              "id": "304ebf01-978f-4f10-afa3-ca39eae013bc",
              "title": "Willian",
              "url": "/en/teams/profile/estevao",
              "isExternal": false,
              "isActive": false
            }
          },
          "playerAdditionalStat": "85%"
        },
        {
          "playerRank": "17th",
          "overallTeamRankingPercent": "85",
          "rankValue": 17,
          "playerAvatar": {
            "lastName": "Fernandez",
            "image": {
              "id": "editorial/people/first-team/2025-26/Enzo_Fernandez_2025-26_profile_with_patch_headshot-removebg",
              "title": "editorial/people/first-team/2025-26/Enzo_Fernandez_2025-26_profile_with_patch_headshot-removebg",
              "description": "",
              "credit": "",
              "file": {
                "fileName": "editorial/people/first-team/2025-26/Enzo_Fernandez_2025-26_profile_with_patch_headshot-removebg",
                "contentType": "image",
                "type": "upload",
                "format": "png",
                "url": "http://img.chelseafc.com/image/upload/v1756766288/editorial/people/first-team/2025-26/Enzo_Fernandez_2025-26_profile_with_patch_headshot-removebg.png",
                "urlObject": {
                  "baseUrl": "https://res.cloudinary.com/",
                  "cloudName": "chelsea-production",
                  "resourceType": "image",
                  "type": "upload",
                  "publicId": "editorial/people/first-team/2025-26/Enzo_Fernandez_2025-26_profile_with_patch_headshot-removebg"
                },
                "details": {
                  "size": 14142518,
                  "transformations": "",
                  "image": {
                    "width": 3333,
                    "height": 3333
                  }
                }
              },
              "coordinates": []
            },
            "profileLink": {
              "id": "bb9a8d94-bee6-4263-8f25-5e448db15b21",
              "title": "Fernandez",
              "url": "/en/teams/profile/enzo-fernandez",
              "isExternal": false,
              "isActive": false
            }
          },
          "playerAdditionalStat": "85%"
        },
        {
          "playerRank": "18th",
          "overallTeamRankingPercent": "84",
          "rankValue": 18,
          "playerAvatar": {
            "lastName": "Santos",
            "image": {
              "id": "editorial/people/first-team/2025-26/Andrey_Santos_2025-26_profile_with_patch_headshot-removebg",
              "title": "editorial/people/first-team/2025-26/Andrey_Santos_2025-26_profile_with_patch_headshot-removebg",
              "description": "",
              "credit": "",
              "file": {
                "fileName": "editorial/people/first-team/2025-26/Andrey_Santos_2025-26_profile_with_patch_headshot-removebg",
                "contentType": "image",
                "type": "upload",
                "format": "png",
                "url": "http://img.chelseafc.com/image/upload/v1756766187/editorial/people/first-team/2025-26/Andrey_Santos_2025-26_profile_with_patch_headshot-removebg.png",
                "urlObject": {
                  "baseUrl": "https://res.cloudinary.com/",
                  "cloudName": "chelsea-production",
                  "resourceType": "image",
                  "type": "upload",
                  "publicId": "editorial/people/first-team/2025-26/Andrey_Santos_2025-26_profile_with_patch_headshot-removebg"
                },
                "details": {
                  "size": 13392851,
                  "transformations": "",
                  "image": {
                    "width": 3333,
                    "height": 3333
                  }
                }
              },
              "coordinates": []
            },
            "profileLink": {
              "id": "a3d8082e-8266-4de8-9fe1-361c2db39957",
              "title": "Santos",
              "url": "/en/teams/profile/andrey-santos",
              "isExternal": false,
              "isActive": false
            }
          },
          "playerAdditionalStat": "84%"
        },
        {
          "playerRank": "19th",
          "overallTeamRankingPercent": "84",
          "rankValue": 19,
          "playerAvatar": {
            "lastName": "Pedro",
            "image": {
              "id": "editorial/people/first-team/2025-26/Joao_Pedro_2025-26_profile_with_patch_headshot_-removebg",
              "title": "editorial/people/first-team/2025-26/Joao_Pedro_2025-26_profile_with_patch_headshot_-removebg",
              "description": "",
              "credit": "",
              "file": {
                "fileName": "editorial/people/first-team/2025-26/Joao_Pedro_2025-26_profile_with_patch_headshot_-removebg",
                "contentType": "image",
                "type": "upload",
                "format": "png",
                "url": "http://img.chelseafc.com/image/upload/v1756847578/editorial/people/first-team/2025-26/Joao_Pedro_2025-26_profile_with_patch_headshot_-removebg.png",
                "urlObject": {
                  "baseUrl": "https://res.cloudinary.com/",
                  "cloudName": "chelsea-production",
                  "resourceType": "image",
                  "type": "upload",
                  "publicId": "editorial/people/first-team/2025-26/Joao_Pedro_2025-26_profile_with_patch_headshot_-removebg"
                },
                "details": {
                  "size": 14380038,
                  "transformations": "",
                  "image": {
                    "width": 3333,
                    "height": 3333
                  }
                }
              },
              "coordinates": []
            },
            "profileLink": {
              "id": "471708eb-bd2e-4555-9011-78b15ff1e2b5",
              "title": "Pedro",
              "url": "/en/teams/profile/joao-pedro",
              "isExternal": false,
              "isActive": false
            }
          },
          "playerAdditionalStat": "84%"
        },
        {
          "playerRank": "20th",
          "overallTeamRankingPercent": "83",
          "rankValue": 20,
          "playerAvatar": {
            "lastName": "Palmer ",
            "image": {
              "id": "editorial/people/first-team/2025-26/Cole_Palmer_2025-26_profile_with_headshot_avatar-removebg",
              "title": "editorial/people/first-team/2025-26/Cole_Palmer_2025-26_profile_with_headshot_avatar-removebg",
              "description": "",
              "credit": "",
              "file": {
                "fileName": "editorial/people/first-team/2025-26/Cole_Palmer_2025-26_profile_with_headshot_avatar-removebg",
                "contentType": "image",
                "type": "upload",
                "format": "png",
                "url": "http://img.chelseafc.com/image/upload/v1756766299/editorial/people/first-team/2025-26/Cole_Palmer_2025-26_profile_with_headshot_avatar-removebg.png",
                "urlObject": {
                  "baseUrl": "https://res.cloudinary.com/",
                  "cloudName": "chelsea-production",
                  "resourceType": "image",
                  "type": "upload",
                  "publicId": "editorial/people/first-team/2025-26/Cole_Palmer_2025-26_profile_with_headshot_avatar-removebg"
                },
                "details": {
                  "size": 12827579,
                  "transformations": "",
                  "image": {
                    "width": 3333,
                    "height": 3333
                  }
                }
              },
              "coordinates": []
            },
            "profileLink": {
              "id": "6121b5cb-9dfc-43b9-87b2-2eba1ac9a751",
              "title": "Palmer ",
              "url": "/en/teams/profile/cole-palmer",
              "isExternal": false,
              "isActive": false
            }
          },
          "playerAdditionalStat": "83%"
        },
        {
          "playerRank": "21st",
          "overallTeamRankingPercent": "76",
          "rankValue": 21,
          "playerAvatar": {
            "lastName": "Jorgensen",
            "image": {
              "id": "editorial/people/first-team/2025-26/Filip_Jorgensen_2025-26_profile_with_patch_headshot-removebg",
              "title": "editorial/people/first-team/2025-26/Filip_Jorgensen_2025-26_profile_with_patch_headshot-removebg",
              "description": "",
              "credit": "",
              "file": {
                "fileName": "editorial/people/first-team/2025-26/Filip_Jorgensen_2025-26_profile_with_patch_headshot-removebg",
                "contentType": "image",
                "type": "upload",
                "format": "png",
                "url": "http://img.chelseafc.com/image/upload/v1756766357/editorial/people/first-team/2025-26/Filip_Jorgensen_2025-26_profile_with_patch_headshot-removebg.png",
                "urlObject": {
                  "baseUrl": "https://res.cloudinary.com/",
                  "cloudName": "chelsea-production",
                  "resourceType": "image",
                  "type": "upload",
                  "publicId": "editorial/people/first-team/2025-26/Filip_Jorgensen_2025-26_profile_with_patch_headshot-removebg"
                },
                "details": {
                  "size": 11095468,
                  "transformations": "",
                  "image": {
                    "width": 3333,
                    "height": 3333
                  }
                }
              },
              "coordinates": []
            },
            "profileLink": {
              "id": "3fa7ec27-813e-4347-bad3-66c6a5b2344e",
              "title": "Jorgensen",
              "url": "/en/teams/profile/filip-jorgensen",
              "isExternal": false,
              "isActive": false
            }
          },
          "playerAdditionalStat": "76%"
        },
        {
          "playerRank": "22nd",
          "overallTeamRankingPercent": "64",
          "rankValue": 22,
          "playerAvatar": {
            "lastName": "Delap",
            "image": {
              "id": "editorial/people/first-team/2025-26/Liam_Delap_2025-26_profile_with_patch_headshot-removebg",
              "title": "editorial/people/first-team/2025-26/Liam_Delap_2025-26_profile_with_patch_headshot-removebg",
              "description": "",
              "credit": "",
              "file": {
                "fileName": "editorial/people/first-team/2025-26/Liam_Delap_2025-26_profile_with_patch_headshot-removebg",
                "contentType": "image",
                "type": "upload",
                "format": "png",
                "url": "http://img.chelseafc.com/image/upload/v1756766436/editorial/people/first-team/2025-26/Liam_Delap_2025-26_profile_with_patch_headshot-removebg.png",
                "urlObject": {
                  "baseUrl": "https://res.cloudinary.com/",
                  "cloudName": "chelsea-production",
                  "resourceType": "image",
                  "type": "upload",
                  "publicId": "editorial/people/first-team/2025-26/Liam_Delap_2025-26_profile_with_patch_headshot-removebg"
                },
                "details": {
                  "size": 14298317,
                  "transformations": "",
                  "image": {
                    "width": 3333,
                    "height": 3333
                  }
                }
              },
              "coordinates": []
            },
            "profileLink": {
              "id": "67bfe3b7-82f9-4670-8d23-cc12dd080c42",
              "title": "Delap",
              "url": "/en/teams/profile/liam-delap",
              "isExternal": false,
              "isActive": false
            }
          },
          "playerAdditionalStat": "64%"
        },
        {
          "playerRank": "23rd",
          "overallTeamRankingPercent": "64",
          "rankValue": 23,
          "playerAvatar": {
            "lastName": "Sanchez",
            "image": {
              "id": "editorial/people/first-team/2025-26/Robert_Sanchez_2025-26_profile_with_patch_headshot-removebg",
              "title": "editorial/people/first-team/2025-26/Robert_Sanchez_2025-26_profile_with_patch_headshot-removebg",
              "description": "",
              "credit": "",
              "file": {
                "fileName": "editorial/people/first-team/2025-26/Robert_Sanchez_2025-26_profile_with_patch_headshot-removebg",
                "contentType": "image",
                "type": "upload",
                "format": "png",
                "url": "http://img.chelseafc.com/image/upload/v1756766591/editorial/people/first-team/2025-26/Robert_Sanchez_2025-26_profile_with_patch_headshot-removebg.png",
                "urlObject": {
                  "baseUrl": "https://res.cloudinary.com/",
                  "cloudName": "chelsea-production",
                  "resourceType": "image",
                  "type": "upload",
                  "publicId": "editorial/people/first-team/2025-26/Robert_Sanchez_2025-26_profile_with_patch_headshot-removebg"
                },
                "details": {
                  "size": 11217126,
                  "transformations": "",
                  "image": {
                    "width": 3333,
                    "height": 3333
                  }
                }
              },
              "coordinates": []
            },
            "profileLink": {
              "id": "a705d9c9-f825-41a1-85b8-df44609be304",
              "title": "Sanchez",
              "url": "/en/teams/profile/robert-sanchez",
              "isExternal": false,
              "isActive": false
            }
          },
          "playerAdditionalStat": "64%"
        },
        {
          "playerRank": "24th",
          "overallTeamRankingPercent": "63",
          "rankValue": 24,
          "playerAvatar": {
            "lastName": "Guiu",
            "image": {
              "id": "editorial/people/first-team/2025-26/Marc_Guiu_profile_2025-26_headshot-removebg",
              "title": "editorial/people/first-team/2025-26/Marc_Guiu_profile_2025-26_headshot-removebg",
              "description": "",
              "credit": "",
              "file": {
                "fileName": "editorial/people/first-team/2025-26/Marc_Guiu_profile_2025-26_headshot-removebg",
                "contentType": "image",
                "type": "upload",
                "format": "png",
                "url": "http://img.chelseafc.com/image/upload/v1749462751/editorial/people/first-team/2025-26/Marc_Guiu_profile_2025-26_headshot-removebg.png",
                "urlObject": {
                  "baseUrl": "https://res.cloudinary.com/",
                  "cloudName": "chelsea-production",
                  "resourceType": "image",
                  "type": "upload",
                  "publicId": "editorial/people/first-team/2025-26/Marc_Guiu_profile_2025-26_headshot-removebg"
                },
                "details": {
                  "size": 12532722,
                  "transformations": "",
                  "image": {
                    "width": 3333,
                    "height": 3333
                  }
                }
              },
              "coordinates": []
            },
            "profileLink": {
              "id": "f6931818-81e2-4442-9130-778248d0c972",
              "title": "Guiu",
              "url": "/en/teams/profile/marc-guiu",
              "isExternal": false,
              "isActive": false
            }
          },
          "playerAdditionalStat": "63%"
        }
      ]
    },
    "touches": {
      "title": "Touches",
      "stats": [
        {
          "title": "Total Touches",
          "value": "373",
          "rankingLabel": "Team Ranking",
          "rank": "8th"
        },
        {
          "title": "Tackles Won / Lost",
          "value": "3/1",
          "rankingLabel": "Team Ranking",
          "rank": "5th"
        },
        {
          "title": "Clearances",
          "value": "2",
          "rankingLabel": "Team Ranking",
          "rank": "12th"
        },
        {
          "title": "Interceptions",
          "value": "4",
          "rankingLabel": "Team Ranking",
          "rank": "6th"
        },
        {
          "title": "Duels Won / Lost",
          "value": "28/31",
          "rankingLabel": "Team Ranking",
          "rank": "11th"
        },
        {
          "title": "Blocks",
          "value": "0",
          "rankingLabel": "Team Ranking",
          "rank": "-"
        }
      ]
    },
    "passCompletion": {
      "title": "Pass Completion %",
      "teamAverageTitle": "Team Average",
      "teamShortPasses": "92",
      "teamLongPasses": "40",
      "playerShortPasses": {
        "title": "Short Balls",
        "value": "87"
      },
      "playerLongPasses": {
        "title": "Long Balls",
        "value": "54"
      }
    },
    "shots": {
      "title": "Shots",
      "shotsOnTargetTitle": "Shots On Target",
      "shotsOffTargetTitle": "Shots Off Target",
      "woodworkHitTitle": "Woodwork Hit",
      "playerTitle": "Player",
      "playerShotsOnTarget": "3",
      "playerShotsOffTarget": "2",
      "playerWoodworkHit": "0",
      "teamAverageTitle": "Team Average",
      "teamShotsOnTarget": "3",
      "teamShotsOffTarget": "3",
      "teamWoodworkHit": "2"
    },
    "seasons": [
      {
        "displayText": "2025/26",
        "value": "2025",
        "selectedValue": true
      },
      {
        "displayText": "2024/25",
        "value": "2024",
        "selectedValue": false
      }
    ],
    "competitions": [
      {
        "displayText": "FA Cup",
        "value": "1",
        "selectedValue": false
      },
      {
        "displayText": "Carabao Cup",
        "value": "2",
        "selectedValue": false
      },
      {
        "displayText": "UEFA Champions League",
        "value": "5",
        "selectedValue": false
      },
      {
        "displayText": "Premier League",
        "value": "8",
        "selectedValue": true
      },
      {
        "displayText": "Friendly",
        "value": "34",
        "selectedValue": false
      },
      {
        "displayText": "UEFA Conference League",
        "value": "1125",
        "selectedValue": false
      },
      {
        "displayText": "UEFA Conference League Qualifier",
        "value": "1126",
        "selectedValue": false
      },
      {
        "displayText": "FIFA Club World Cup ",
        "value": "1277",
        "selectedValue": false
      }
    ]
  }
}